mlscraper/__init__.py
mlscraper/ml.py
mlscraper/parser.py
mlscraper/training.py
mlscraper/util.py
mlscraper-0.1.2.dist-info/AUTHORS.rst
mlscraper-0.1.2.dist-info/METADATA
mlscraper-0.1.2.dist-info/WHEEL
mlscraper-0.1.2.dist-info/top_level.txt
mlscraper-0.1.2.dist-info/RECORD
