Metadata-Version: 2.1
Name: mlscraper
Version: 0.1.2
Summary: Scrape HTML automatically with machine learning.
Home-page: https://github.com/lorey/mlscraper
Author: Karl Lorey
Author-email: git@karllorey.com
License: UNKNOWN
Keywords: mlscraper
Platform: UNKNOWN
Classifier: Development Status :: 2 - Pre-Alpha
Classifier: Intended Audience :: Developers
Classifier: Natural Language :: English
Classifier: Programming Language :: Python :: 3
Classifier: Programming Language :: Python :: 3.5
Classifier: Programming Language :: Python :: 3.6
Classifier: Programming Language :: Python :: 3.7
Classifier: Programming Language :: Python :: 3.8
Requires-Python: >=3.5
Requires-Dist: beautifulsoup4
Requires-Dist: lxml
Requires-Dist: more-itertools (>=8)
Requires-Dist: pandas
Requires-Dist: requests
Requires-Dist: scikit-learn
